vk/__init__.py
vk/api.py
vk/error.py
vk/last_seen.py
vk/mutuals.py
vk/platform.py
vk/user.py
vk/version.py
vk/tracking/__init__.py
vk/tracking/sessions.py
vk/tracking/status.py
vk/tracking/db/__init__.py
vk/tracking/db/format.py
vk/tracking/db/meta.py
vk/tracking/db/record.py
vk/tracking/db/timestamp.py
vk/tracking/db/backend/__init__.py
vk/tracking/db/backend/csv.py
vk/tracking/db/backend/log.py
vk/tracking/db/backend/null.py
vk/utils/__init__.py
vk/utils/bar_chart.py
vk/utils/io.py
vk_scripts-1.0.3.dist-info/LICENSE.txt
vk_scripts-1.0.3.dist-info/METADATA
vk_scripts-1.0.3.dist-info/WHEEL
vk_scripts-1.0.3.dist-info/entry_points.txt
vk_scripts-1.0.3.dist-info/top_level.txt
vk_scripts-1.0.3.dist-info/RECORD
