Metadata-Version: 2.1
Name: vk-scripts
Version: 1.0.3
Summary: Scripts to stalk people on VK
Author-email: Egor Tensin <Egor.Tensin@gmail.com>
License: MIT
Project-URL: Homepage, https://github.com/egor-tensin/vk-scripts
Project-URL: Bug Tracker, https://github.com/egor-tensin/vk-scripts/issues
Classifier: Development Status :: 4 - Beta
Classifier: License :: OSI Approved :: MIT License
Requires-Python: >=3.4
License-File: LICENSE.txt
Requires-Dist: matplotlib
Requires-Dist: importlib-metadata (~=4.0) ; python_version < "3.8"
